MANIFEST.in
README.md
setup.py
benchs/0.bch
benchs/0_.bch
benchs/1.bch
benchs/exnewton.bch
benchs/forgint.bch
icpy/__init__.py
icpy/box.py
icpy/contractor.py
icpy/contractor_box.py
icpy/contractor_hull.py
icpy/contractor_newton.py
icpy/csp_parser.py
icpy/csp_semantics.py
icpy/dag.py
icpy/interval_utils.py
icpy/solver.py
icpy_solver.egg-info/PKG-INFO
icpy_solver.egg-info/SOURCES.txt
icpy_solver.egg-info/dependency_links.txt
icpy_solver.egg-info/entry_points.txt
icpy_solver.egg-info/not-zip-safe
icpy_solver.egg-info/requires.txt
icpy_solver.egg-info/top_level.txt