Metadata-Version: 1.0
Name: icpy-solver
Version: 0.0.1
Summary: An interval constraint programming tool
Home-page: https://github.com/dsksh/ICPy
Author: Daisuke Ishii
Author-email: dsksh@acm.org
License: MIT
Platform: UNKNOWN
